{
  "/api/carrito/route": "app/api/carrito/route.js",
  "/api/orders/[orderId]/route": "app/api/orders/[orderId]/route.js",
  "/api/products/[id]/route": "app/api/products/[id]/route.js",
  "/api/orders/route": "app/api/orders/route.js",
  "/api/webhooks/mercadopago/route": "app/api/webhooks/mercadopago/route.js",
  "/api/products/route": "app/api/products/route.js",
  "/_not-found/page": "app/_not-found/page.js",
  "/admin/page": "app/admin/page.js",
  "/historia/page": "app/historia/page.js",
  "/cart/page": "app/cart/page.js",
  "/checkout/page": "app/checkout/page.js",
  "/login/page": "app/login/page.js",
  "/latas/page": "app/latas/page.js",
  "/mi-cuenta/order/[orderId]/page": "app/mi-cuenta/order/[orderId]/page.js",
  "/mi-cuenta/page": "app/mi-cuenta/page.js",
  "/ofertas/page": "app/ofertas/page.js",
  "/page": "app/page.js",
  "/productos/page": "app/productos/page.js"
}